libname/__init__.py
libname/main.py
Speaking_Alex_voice_assistant-0.1.2.dist-info/METADATA
Speaking_Alex_voice_assistant-0.1.2.dist-info/WHEEL
Speaking_Alex_voice_assistant-0.1.2.dist-info/top_level.txt
Speaking_Alex_voice_assistant-0.1.2.dist-info/RECORD
